{
  "_class": "symbolInstance",
  "do_objectID": "B84E18BE-4D56-4F31-BFD1-4F94204CB2B3",
  "exportOptions": {
    "_class": "exportOptions",
    "exportFormats": [
    ],
    "includedLayerIds": [
    ],
    "layerOptions": 0,
    "shouldTrim": false
  },
  "frame": {
    "_class": "rect",
    "constrainProportions": false,
    "do_objectID": "8C6E6E35-D1CD-4A30-965F-155F9BEC1CCC",
    "height": 186,
    "width": 388,
    "x": 113,
    "y": 427
  },
  "horizontalSpacing": 0,
  "isFlippedHorizontal": false,
  "isFlippedVertical": false,
  "isLocked": false,
  "isVisible": true,
  "layerListExpandedType": 0,
  "name": "Component/Card/EventCard",
  "nameIsFixed": false,
  "overrideValues": [
  ],
  "overrides": {
  },
  "resizingConstraint": 63,
  "resizingType": 0,
  "rotation": 0,
  "scale": 1,
  "shouldBreakMaskChain": false,
  "style": {
    "_class": "style",
    "do_objectID": "80C34A0C-9C47-4D93-99DA-DA4F711276F8",
    "endDecorationType": 0,
    "miterLimit": 10,
    "startDecorationType": 0
  },
  "symbolID": "85C981B9-1077-408C-A205-786E14B49188",
  "verticalSpacing": 0
}