{
  "_class": "group",
  "do_objectID": "ACBF4D3F-1C6F-41DD-A1EF-07F3ED3D8695",
  "exportOptions": {
    "_class": "exportOptions",
    "exportFormats": [
    ],
    "includedLayerIds": [
    ],
    "layerOptions": 0,
    "shouldTrim": false
  },
  "frame": {
    "_class": "rect",
    "constrainProportions": true,
    "height": 24,
    "width": 24,
    "x": 388,
    "y": 310
  },
  "hasClickThrough": false,
  "isFlippedHorizontal": false,
  "isFlippedVertical": false,
  "isLocked": false,
  "isVisible": true,
  "layerListExpandedType": 0,
  "layers": [
    {
      "class": "shapeGroup",
      "id": "0976175E-D9D6-4153-B4BB-C103CCE3EC45"
    },
    {
      "class": "group",
      "id": "B0322805-EBDA-4335-992D-450EBC081CE0"
    }
  ],
  "name": "Group 59",
  "nameIsFixed": false,
  "resizingConstraint": 63,
  "resizingType": 0,
  "rotation": 0,
  "shouldBreakMaskChain": false,
  "style": {
    "_class": "style",
    "contextSettings": {
      "_class": "graphicsContextSettings",
      "blendMode": 0,
      "opacity": 0.65
    },
    "endDecorationType": 0,
    "miterLimit": 10,
    "startDecorationType": 0
  },
  "userInfo": {
    "com.animaapp.stc-sketch-plugin": {
      "kModelPropertiesKey": {
        "constraints": {
          "aspectRatio": {
            "constant": 24,
            "enabled": 1,
            "modelID": "constraint_1b052703-9dec-4756-b4df-8dc45e19b1ab",
            "model_class": "ADModelConstraint",
            "model_version": 0.1,
            "multiplier": 24
          },
          "automatic": 1,
          "modelID": "viewConstraints_95e8e0fb-2af5-4888-88d6-6fa7202ce6d9",
          "model_class": "ADModelViewConstraints",
          "model_version": 0.1,
          "scaleFactor": 1
        }
      }
    }
  }
}