{
  "_class": "shapePath",
  "booleanOperation": -1,
  "do_objectID": "A0F0FACA-E7CD-4BB9-AC05-146F1545C75A",
  "edited": true,
  "exportOptions": {
    "_class": "exportOptions",
    "exportFormats": [
    ],
    "includedLayerIds": [
    ],
    "layerOptions": 0,
    "shouldTrim": false
  },
  "frame": {
    "_class": "rect",
    "constrainProportions": false,
    "height": 12.42719999999999,
    "width": 13.89084639498434,
    "x": 25.81617554858938,
    "y": 4.772282328919912
  },
  "isClosed": true,
  "isFlippedHorizontal": false,
  "isFlippedVertical": false,
  "isLocked": false,
  "isVisible": true,
  "layerListExpandedType": 0,
  "name": "Fill-8-path",
  "nameIsFixed": false,
  "path": {
    "_class": "path",
    "isClosed": true,
    "pointRadiusBehaviour": 0,
    "points": [
      {
        "_class": "curvePoint",
        "cornerRadius": 0,
        "curveFrom": "{0.94966126404253526, 0}",
        "curveMode": 1,
        "curveTo": "{0.94966126404253526, 0}",
        "hasCurveFrom": false,
        "hasCurveTo": false,
        "point": "{0.94966126404253526, 0}"
      },
      {
        "_class": "curvePoint",
        "cornerRadius": 0,
        "curveFrom": "{0, 1}",
        "curveMode": 1,
        "curveTo": "{0, 1}",
        "hasCurveFrom": false,
        "hasCurveTo": false,
        "point": "{0, 1}"
      },
      {
        "_class": "curvePoint",
        "cornerRadius": 0,
        "curveFrom": "{1, 0.4831015836230203}",
        "curveMode": 1,
        "curveTo": "{1, 0.4831015836230203}",
        "hasCurveFrom": false,
        "hasCurveTo": false,
        "point": "{1, 0.4831015836230203}"
      },
      {
        "_class": "curvePoint",
        "cornerRadius": 0,
        "curveFrom": "{0.94966126404253526, 0}",
        "curveMode": 1,
        "curveTo": "{0.94966126404253526, 0}",
        "hasCurveFrom": false,
        "hasCurveTo": false,
        "point": "{0.94966126404253526, 0}"
      }
    ]
  },
  "pointRadiusBehaviour": 0,
  "points": [
    {
      "_class": "curvePoint",
      "cornerRadius": 0,
      "curveFrom": "{0.94966126404253526, 0}",
      "curveMode": 1,
      "curveTo": "{0.94966126404253526, 0}",
      "hasCurveFrom": false,
      "hasCurveTo": false,
      "point": "{0.94966126404253526, 0}"
    },
    {
      "_class": "curvePoint",
      "cornerRadius": 0,
      "curveFrom": "{0, 1}",
      "curveMode": 1,
      "curveTo": "{0, 1}",
      "hasCurveFrom": false,
      "hasCurveTo": false,
      "point": "{0, 1}"
    },
    {
      "_class": "curvePoint",
      "cornerRadius": 0,
      "curveFrom": "{1, 0.4831015836230203}",
      "curveMode": 1,
      "curveTo": "{1, 0.4831015836230203}",
      "hasCurveFrom": false,
      "hasCurveTo": false,
      "point": "{1, 0.4831015836230203}"
    },
    {
      "_class": "curvePoint",
      "cornerRadius": 0,
      "curveFrom": "{0.94966126404253526, 0}",
      "curveMode": 1,
      "curveTo": "{0.94966126404253526, 0}",
      "hasCurveFrom": false,
      "hasCurveTo": false,
      "point": "{0.94966126404253526, 0}"
    }
  ],
  "resizingConstraint": 63,
  "resizingType": 0,
  "rotation": 0,
  "shouldBreakMaskChain": false
}