{
  "_class": "page",
  "do_objectID": "0EC89917-F949-4461-A7B3-32A5201FD2A2",
  "exportOptions": {
    "_class": "exportOptions",
    "exportFormats": [
    ],
    "includedLayerIds": [
    ],
    "layerOptions": 0,
    "shouldTrim": false
  },
  "frame": {
    "_class": "rect",
    "constrainProportions": false,
    "height": 300,
    "width": 300,
    "x": 0,
    "y": 0
  },
  "hasClickThrough": true,
  "horizontalRulerData": {
    "_class": "rulerData",
    "base": 0,
    "guides": [
    ]
  },
  "includeInCloudUpload": true,
  "isFlippedHorizontal": false,
  "isFlippedVertical": false,
  "isLocked": false,
  "isVisible": true,
  "layerListExpandedType": 0,
  "layers": [
    {
      "class": "artboard",
      "id": "4C31890D-E591-4E7B-B948-A48C0AA44242"
    },
    {
      "class": "artboard",
      "id": "A0C6BBED-9359-4B21-B673-7B69ABE7D974"
    },
    {
      "class": "artboard",
      "id": "4B56E3AB-A926-4900-BE85-19A9A3EA7874"
    },
    {
      "class": "artboard",
      "id": "9F2794D8-0FEB-4506-8F93-3037598070D9"
    },
    {
      "class": "artboard",
      "id": "DFF6BDC3-F622-4F94-B62E-6DF1885DE5ED"
    },
    {
      "class": "artboard",
      "id": "C0D98C08-BE91-47E7-888D-654D7CDF77CF"
    },
    {
      "class": "artboard",
      "id": "D73ED9E1-5E6E-48C9-A070-B9424DD6D4B6"
    },
    {
      "class": "artboard",
      "id": "F77A909F-4A66-4F08-AE1E-DE74284D2CE9"
    },
    {
      "class": "artboard",
      "id": "717B68C7-3952-44E3-9F35-F1297335B987"
    },
    {
      "class": "artboard",
      "id": "E74AA7C7-90C8-4F17-A94F-C6E82A497AFB"
    },
    {
      "class": "artboard",
      "id": "B143DB3E-1905-46E8-AAAC-13C8A0B54BA8"
    },
    {
      "class": "artboard",
      "id": "A9F4F643-4651-4B5B-86D9-2B31B6EEE786"
    },
    {
      "class": "artboard",
      "id": "BEFB8F0F-F502-4939-A7D3-26691C7A0EC4"
    }
  ],
  "name": "Screens",
  "nameIsFixed": false,
  "resizingConstraint": 0,
  "resizingType": 0,
  "rotation": 0,
  "shouldBreakMaskChain": false,
  "style": {
    "_class": "style",
    "endDecorationType": 0,
    "miterLimit": 10,
    "startDecorationType": 0
  },
  "userInfo": {
  },
  "verticalRulerData": {
    "_class": "rulerData",
    "base": 0,
    "guides": [
    ]
  }
}