{
  "_class": "group",
  "do_objectID": "E763B200-C77C-445C-9E89-1EEA68F91040",
  "exportOptions": {
    "_class": "exportOptions",
    "exportFormats": [
    ],
    "includedLayerIds": [
    ],
    "layerOptions": 0,
    "shouldTrim": false
  },
  "frame": {
    "_class": "rect",
    "constrainProportions": false,
    "height": 13,
    "width": 27,
    "x": 135,
    "y": 5
  },
  "hasClickThrough": false,
  "isFlippedHorizontal": false,
  "isFlippedVertical": false,
  "isLocked": false,
  "isVisible": true,
  "layerListExpandedType": 0,
  "layers": [
    {
      "class": "shapeGroup",
      "id": "19016AFE-24F8-4E2D-972D-D217AABC706F"
    },
    {
      "class": "shapeGroup",
      "id": "9B8F2170-7FA6-46B0-845B-E5E1B00460A5"
    }
  ],
  "name": "Group",
  "nameIsFixed": false,
  "resizingConstraint": 12,
  "resizingType": 0,
  "rotation": 0,
  "shouldBreakMaskChain": false,
  "style": {
    "_class": "style",
    "endDecorationType": 0,
    "miterLimit": 10,
    "startDecorationType": 0
  }
}