{
  "_class": "group",
  "do_objectID": "F6617009-667E-4DFF-9344-0231A86452DA",
  "exportOptions": {
    "_class": "exportOptions",
    "exportFormats": [
    ],
    "includedLayerIds": [
    ],
    "layerOptions": 0,
    "shouldTrim": false
  },
  "frame": {
    "_class": "rect",
    "constrainProportions": true,
    "height": 24,
    "width": 24,
    "x": 820,
    "y": 366
  },
  "hasClickThrough": false,
  "isFlippedHorizontal": false,
  "isFlippedVertical": false,
  "isLocked": false,
  "isVisible": true,
  "layerListExpandedType": 0,
  "layers": [
    {
      "class": "shapeGroup",
      "id": "EDD9CDC7-F7BA-4605-BC6A-1557C3A27555"
    },
    {
      "class": "group",
      "id": "F4D55831-A5B8-4CA4-9D3F-E08E737ABA51"
    }
  ],
  "name": "Group 52",
  "nameIsFixed": false,
  "resizingConstraint": 63,
  "resizingType": 0,
  "rotation": 0,
  "shouldBreakMaskChain": false,
  "style": {
    "_class": "style",
    "contextSettings": {
      "_class": "graphicsContextSettings",
      "blendMode": 0,
      "opacity": 0.65
    },
    "endDecorationType": 0,
    "miterLimit": 10,
    "startDecorationType": 0
  },
  "userInfo": {
    "com.animaapp.stc-sketch-plugin": {
      "kModelPropertiesKey": {
        "constraints": {
          "aspectRatio": {
            "constant": 24,
            "enabled": 1,
            "modelID": "constraint_010b19b1-b201-4888-bd3b-129708df264b",
            "model_class": "ADModelConstraint",
            "model_version": 0.1,
            "multiplier": 24
          },
          "automatic": 1,
          "modelID": "viewConstraints_500dfaf5-fbd8-42a5-a2e4-fdbb6b5939dc",
          "model_class": "ADModelViewConstraints",
          "model_version": 0.1,
          "scaleFactor": 1
        }
      }
    }
  }
}